{
  "experiment": "expression_noise_filtered",
  "description": "Reanalysis of gene expression noise vs TF regulator count, addressing reviewer concerns about selection bias, measurement artifacts, and small N.",
  "artifact_genes_removed": [
    "FLO1",
    "GAL1",
    "GAL10",
    "HO",
    "IME1"
  ],
  "artifact_removal_reason": "GAL1, GAL10: galactose-inducible, essentially OFF in glucose (standard conditions); measured 'noise' is shot noise from near-zero expression. HO: mating-type switch, silenced in most lab strains. IME1: meiosis-specific, repressed in mitotic growth. FLO1: epigenetically silenced, subtelomeric.",
  "quality_filters": {
    "expression_threshold_log2": 6.64,
    "expression_threshold_molecules_per_cell": 100,
    "min_tf_regulators": 2,
    "rationale": "Exclude genes with mean expression below 100 molecules/cell (removes shot noise artifacts where measured CV\u00b2 reflects Poisson sampling rather than regulatory noise). Exclude genes with fewer than 2 known TF regulators (can't assess regulatory complexity)."
  },
  "confounders_controlled": [
    "expression_level_log2",
    "TATA_box_presence",
    "essentiality"
  ],
  "results": {
    "full_40_genes": {
      "label": "A. Full dataset (40 genes, original)",
      "n_genes": 41,
      "genes": [
        "GAL1",
        "GAL10",
        "PHO5",
        "HIS4",
        "SUC2",
        "CYC1",
        "ADH2",
        "FLO1",
        "ACT1",
        "PGK1",
        "TDH3",
        "ENO2",
        "CDC28",
        "CLN3",
        "SWI4",
        "MBP1",
        "CLB2",
        "TUB1",
        "RPL3",
        "RPL25",
        "RPS5",
        "RPL16A",
        "RPS3",
        "RPL5",
        "NOP1",
        "SEC61",
        "SSA1",
        "HSP82",
        "SSB1",
        "KAR2",
        "HO",
        "IME1",
        "SPO11",
        "URA3",
        "LEU2",
        "TRP1",
        "ADE2",
        "LYS2",
        "MET3",
        "GCN4",
        "HAP4"
      ],
      "raw_spearman_rho": 0.7804,
      "raw_spearman_p": 1.7804219623834283e-09,
      "partial_spearman_rho": 0.5068,
      "partial_spearman_p": 0.0007218787896247701,
      "partial_pearson_r": 0.6031,
      "partial_pearson_p": 3.0014053103686153e-05,
      "prediction_supported": true,
      "partial_supported": true
    },
    "no_artifacts_35_genes": {
      "label": "B. Artifacts removed (GAL1, GAL10, HO, IME1, FLO1)",
      "n_genes": 36,
      "genes": [
        "PHO5",
        "HIS4",
        "SUC2",
        "CYC1",
        "ADH2",
        "ACT1",
        "PGK1",
        "TDH3",
        "ENO2",
        "CDC28",
        "CLN3",
        "SWI4",
        "MBP1",
        "CLB2",
        "TUB1",
        "RPL3",
        "RPL25",
        "RPS5",
        "RPL16A",
        "RPS3",
        "RPL5",
        "NOP1",
        "SEC61",
        "SSA1",
        "HSP82",
        "SSB1",
        "KAR2",
        "SPO11",
        "URA3",
        "LEU2",
        "TRP1",
        "ADE2",
        "LYS2",
        "MET3",
        "GCN4",
        "HAP4"
      ],
      "raw_spearman_rho": 0.8162,
      "raw_spearman_p": 1.298351769399762e-09,
      "partial_spearman_rho": 0.5704,
      "partial_spearman_p": 0.000281236461980142,
      "partial_pearson_r": 0.6555,
      "partial_pearson_p": 1.4304439647515944e-05,
      "prediction_supported": true,
      "partial_supported": true
    },
    "quality_filtered": {
      "label": "C. Quality-filtered (expr > 6.6 log2, TF >= 2)",
      "n_genes": 33,
      "genes": [
        "HIS4",
        "SUC2",
        "CYC1",
        "ADH2",
        "ACT1",
        "PGK1",
        "TDH3",
        "ENO2",
        "CDC28",
        "CLN3",
        "SWI4",
        "MBP1",
        "CLB2",
        "TUB1",
        "RPL3",
        "RPL25",
        "RPS5",
        "RPL16A",
        "RPL5",
        "NOP1",
        "SEC61",
        "SSA1",
        "HSP82",
        "SSB1",
        "KAR2",
        "URA3",
        "LEU2",
        "TRP1",
        "ADE2",
        "LYS2",
        "MET3",
        "GCN4",
        "HAP4"
      ],
      "raw_spearman_rho": 0.8676,
      "raw_spearman_p": 6.356198731590599e-11,
      "partial_spearman_rho": 0.7239,
      "partial_spearman_p": 1.92015614113936e-06,
      "partial_pearson_r": 0.7646,
      "partial_pearson_p": 2.22464654165195e-07,
      "prediction_supported": true,
      "partial_supported": true
    },
    "sensitivity_no_artifacts_trimmed": {
      "label": "D. Artifacts removed (trimmed top/bottom 3)",
      "n_genes": 30,
      "genes": [
        "RPL5",
        "RPL25",
        "RPL16A",
        "NOP1",
        "TDH3",
        "SEC61",
        "ACT1",
        "PGK1",
        "ENO2",
        "SSB1",
        "TUB1",
        "KAR2",
        "SSA1",
        "HSP82",
        "CDC28",
        "MBP1",
        "SWI4",
        "HAP4",
        "CLB2",
        "TRP1",
        "CLN3",
        "ADE2",
        "LEU2",
        "LYS2",
        "URA3",
        "GCN4",
        "MET3",
        "CYC1",
        "HIS4",
        "ADH2"
      ],
      "raw_spearman_rho": 0.8315,
      "raw_spearman_p": 1.2601785282879231e-08,
      "partial_spearman_rho": 0.7023,
      "partial_spearman_p": 1.5207462313148828e-05,
      "partial_pearson_r": 0.7757,
      "partial_pearson_p": 4.779963267366978e-07,
      "prediction_supported": true,
      "partial_supported": true
    },
    "sensitivity_filtered_trimmed": {
      "label": "E. Quality-filtered (trimmed top/bottom 3)",
      "n_genes": 27,
      "genes": [
        "RPL5",
        "RPL16A",
        "NOP1",
        "TDH3",
        "SEC61",
        "ACT1",
        "PGK1",
        "ENO2",
        "SSB1",
        "TUB1",
        "KAR2",
        "SSA1",
        "CDC28",
        "HSP82",
        "MBP1",
        "SWI4",
        "HAP4",
        "CLB2",
        "TRP1",
        "CLN3",
        "ADE2",
        "LEU2",
        "LYS2",
        "URA3",
        "GCN4",
        "MET3",
        "CYC1"
      ],
      "raw_spearman_rho": 0.782,
      "raw_spearman_p": 1.456133971096147e-06,
      "partial_spearman_rho": 0.6838,
      "partial_spearman_p": 8.426035647196949e-05,
      "partial_pearson_r": 0.79,
      "partial_pearson_p": 9.576644224255547e-07,
      "prediction_supported": true,
      "partial_supported": true
    }
  },
  "conclusion": {
    "artifact_removal_changes_result": false,
    "correlation_survives_artifact_removal": true,
    "correlation_survives_quality_filter": true,
    "correlation_survives_sensitivity": true,
    "partial_correlation_survives": true
  }
}